act_dr6_mflike/__init__.py
act_dr6_mflike/_version.py
act_dr6_mflike/act_dr6.yaml
act_dr6_mflike/act_dr6_mflike.py
act_dr6_mflike/params_systematics.yaml
act_dr6_mflike/tests/test_act_dr6_mflike.py
act_dr6_mflike-1.0.0.dist-info/licenses/LICENSE
examples/act_dr6_example.yml
act_dr6_mflike-1.0.0.dist-info/METADATA
act_dr6_mflike-1.0.0.dist-info/WHEEL
act_dr6_mflike-1.0.0.dist-info/top_level.txt
act_dr6_mflike-1.0.0.dist-info/RECORD
