Metadata-Version: 2.4
Name: act_dr6_mflike
Version: 1.0.0
Summary: ACT DR6 multi-frequency likelihood for cobaya
License: 
Project-URL: Homepage, https://github.com/ACTCollaboration/act_dr6_mflike
Project-URL: Source, https://github.com/ACTCollaboration/act_dr6_mflike
Project-URL: Tracker, https://github.com/ACTCollaboration/act_dr6_mflike/issues
Project-URL: Licensing, https://github.com/ACTCollaboration/act_dr6_mflike/main/LICENCE
Keywords: likelihood,ACT,DR6,cosmology
Classifier: Development Status :: 2 - Pre-Alpha
Classifier: Intended Audience :: Developers
Classifier: License :: OSI Approved :: BSD License
Classifier: Natural Language :: English
Classifier: Programming Language :: Python :: 3.9
Classifier: Programming Language :: Python :: 3.10
Classifier: Programming Language :: Python :: 3.11
Requires-Python: >=3.9.0
License-File: LICENSE
Requires-Dist: mflike>=1.0.0
Provides-Extra: test
Requires-Dist: pytest; extra == "test"
Requires-Dist: pytest-cov; extra == "test"
Requires-Dist: camb; extra == "test"
Dynamic: license-file
